oboe/__init__.py
oboe/auto_learner.py
oboe/convex_opt.py
oboe/ensemble.py
oboe/experiment_design.py
oboe/generate_vector.py
oboe/linalg.py
oboe/model.py
oboe/pipeline.py
oboe/preprocessing.py
oboe/util.py
oboe/defaults/.DS_Store
oboe/defaults/Oboe/classification.json
oboe/defaults/Oboe/dataset_sizes.csv
oboe/defaults/Oboe/error_matrix.csv
oboe/defaults/Oboe/regression.json
oboe/defaults/Oboe/runtime_matrix.csv
oboe/defaults/Oboe/runtime_predictor.pkl
oboe/defaults/TensorOboe/.DS_Store
oboe/defaults/TensorOboe/classification.json
oboe/defaults/TensorOboe/error_tensor_imputed_20-4-2-2-8-20_f16_compressed.npz
oboe/defaults/TensorOboe/runtime_predictors.pkl
oboe/defaults/TensorOboe/runtime_tensor_f16_compressed.npz
oboe/defaults/TensorOboe/training_index.pkl
oboe/defaults/TensorOboe/tmp/error_tensor_S_t.npy
oboe/defaults/TensorOboe/tmp/error_tensor_U_t.npy
oboe/defaults/TensorOboe/tmp/error_tensor_Vt_t.npy
oboe-0.2.0.dist-info/LICENSE.txt
oboe-0.2.0.dist-info/METADATA
oboe-0.2.0.dist-info/WHEEL
oboe-0.2.0.dist-info/top_level.txt
oboe-0.2.0.dist-info/RECORD
