Metadata-Version: 2.1
Name: oboe
Version: 0.2.0
Summary: An AutoML pipeline selection system to quickly select a promising pipeline for a new dataset.
Home-page: https://github.com/udellgroup/oboe
Author: Chengrun Yang, Yuji Akimoto, Dae Won Kim, Madeleine Udell
Author-email: cy438@cornell.edu
License: UNKNOWN
Project-URL: Bug Tracker, https://github.com/udellgroup/oboe/issues
Platform: UNKNOWN
Classifier: Development Status :: 4 - Beta
Classifier: Programming Language :: Python :: 3
Classifier: License :: OSI Approved :: BSD License
Classifier: Operating System :: OS Independent
Requires-Python: >=3.7
License-File: LICENSE.txt
Requires-Dist: numpy (>=1.16.4)
Requires-Dist: scipy (>=1.4.1)
Requires-Dist: pandas (>=0.24.2)
Requires-Dist: scikit-learn (>=0.22.1)
Requires-Dist: tensorly (==0.6.0)
Requires-Dist: OpenML (>=0.9.0)
Requires-Dist: mkl (>=1.0.0)
